xdai/__init__.py
xdai/designer.py
xdai/gpr.py
xdai/process.py
xdai/softmax.py
xdai/xdai.py
XDAI-0.1.dist-info/METADATA
XDAI-0.1.dist-info/WHEEL
XDAI-0.1.dist-info/top_level.txt
XDAI-0.1.dist-info/RECORD
