Metadata-Version: 2.1
Name: XDAI
Version: 0.1
Summary: Artificial intelligence for experimental design
Home-page: https://github.uio.no/hazelbright/xdai
Author: Audun Skau Hansen, Elias Dalan and Hanan Gharayba
Author-email: a.s.hansen@kjemi.uio.no
Classifier: Programming Language :: Python :: 3
Classifier: License :: OSI Approved :: MIT License
Classifier: Operating System :: OS Independent
Requires-Dist: numpy
Requires-Dist: scipy
Requires-Dist: matplotlib
